{"Success":true,"Response":{"2581":"007 - The World is Not Enough","4080":"Alfred's Adventure","4950":"Antz","4099":"Arthur's Absolutely Fun Day!","2501":"Asterix and Obelix","10659":"Barbie Ocean Discovery","6135":"Beatmania GB","6171":"Beatmania GB2 - GotchaMix","7107":"Bomberman Max: Blue Champion","7102":"Bomberman Max: Red Challenger ","11165":"Bugs Bunny and Lola Bunny: Operation Carrot Patch","4871":"Centipede","4182":"Chicken Run","6526":"Commander Keen","4893":"Conker's Pocket Tales","4184":"Croc","7130":"Dance Dance Revolution GB","12842":"Dance Dance Revolution GB 2","6181":"Dance Dance Revolution GB: Disney Mix","12804":"Detective Conan - The Mechanical Temple Murder Case","5594":"Dragon Ball Z - Legendary Super Warriors","4915":"Dragon Warrior Monsters 2: Tara's Adventure","4301":"Fix and Foxi - Episode 1 Lupo","4129":"Frogger","5369":"Game & Watch Gallery 2","6533":"Game & Watch Gallery 3","6791":"Gex 3 - Deep Pocket Gecko","4920":"Hamtaro: Ham Ham's Unite","2547":"Harry Potter and the Sorcerer's Stone","5155":"Harvest Moon 2","5143":"Harvest Moon 3","5151":"Harvest Moon GB","5371":"Legend of Zelda, The - Link''s Awakening DX","6203":"Lucky Luke","3625":"M and M's Minis Madness","1403":"Mario Golf","5043":"Mario Tennis","713":"Mega Man Xtreme","4912":"Mega Man Xtreme 2 ","4972":"Megami Tensei Gaiden: Last Bible","520":"Metal Gear Solid: Ghost Babel","5042":"Monster Rancher Explorer","4193":"Monsters, Inc.","3650":"Mr. Nutz","10631":"MTV Sports - Skateboarding featuring Andy MacDonald","810":"Pokemon - Crystal Version","576":"Pokemon - Gold Version","722":"Pokemon - Silver Version","725":"Pokemon Pinball","727":"Pokemon Trading Card Game","6169":"Pop&#39;n Music GB: Animated Melody","6167":"Pop'n Music GB","4671":"Powerpuff Girls - Bad Mojo Jojo","3626":"Puzzled","4919":"Quest: Brian's Journey","537":"Rayman","7146":"Santa Claus Junior","4933":"ShadowGate Classic","728":"Shantae","3607":"Street Fighter Alpha: Warriors' Dreams","732":"Super Mario Bros. Deluxe","4923":"Survival Kids","4939":"Tetris DX","3646":"The Grinch","3658":"Tiny Toon Adventures: Buster Saves The Day","741":"Wario Land 3","4922":"Warlocked","4126":"WWF Betrayal","4940":"Xtreme Sports","577":"Yu-Gi-Oh! Dark Duel Stories","12399":"~Bonus~ Legend of Zelda, The: Oracle of Ages & Seasons","6251":"~Hack~ Legend of Zelda, The - Hard Awakening DX","8239":"~Unlicensed~ Zook Hero 2","8228":"~Unlicensed~ Zook Hero Z"}}